{"Exif":{"Lat":0,"Long":0,"Date":"2018-02-25T22:18:21Z","Tags":{"ApertureValue":2,"BrightnessValue":1.23,"ComponentsConfiguration":"","CustomRendered|int":"1","DateTimeDigitized|time.Time":"2018-02-25T22:18:21Z","DateTimeOriginal|time.Time":"2018-02-25T22:18:21Z","DateTime|time.Time":"2018-02-25T22:18:21Z","ExposureTime":0.015767,"FNumber":2,"FocalLength":4.67,"FocalLengthIn35mmFilm|int":"26","ISOSpeedRatings|int":"337","ImageLength|int":"3840","ImageUniqueID":"be10c04b3d20a9ec0000000000000000","ImageWidth|int":"2160","InteroperabilityIFDPointer|int":"846","InteroperabilityIndex":"R98","Make":"Huawei","MaxApertureValue":2,"Model":"Nexus 6P","Orientation|int":"1","PixelXDimension|int":"2160","PixelYDimension|int":"3840","SceneCaptureType|int":"0","SceneType":"","ShutterSpeedValue":5.99,"Software":"HDR+ 1.0.177471000n","SubSecTime":"952337","SubSecTimeDigitized":"952337","SubSecTimeOriginal":"952337","SubjectDistance":0.139,"SubjectDistanceRange|int":"1","YCbCrPositioning|int":"1"}}}
