{"Exif":{"Lat":42.91801997222222,"Long":-7.5033289722222225,"Date":"2018-07-28T10:28:43Z","Tags":{"ApertureValue":1.53,"BrightnessValue":-1.94,"ComponentsConfiguration":"","DateTimeDigitized|time.Time":"2018-07-28T10:28:43Z","DateTimeOriginal|time.Time":"2018-07-28T10:28:43Z","DateTime|time.Time":"2018-07-28T10:28:43Z","ExposureTime|*big.Rat":"1/50","FNumber":1.7,"FocalLength":4.25,"FocalLengthIn35mmFilm|int":"25","ISOSpeedRatings|int":"400","ImageLength|int":"3456","ImageWidth|int":"4608","InteroperabilityIFDPointer|int":"721","InteroperabilityIndex":"R98","LightSource|int":"0","Make":"OnePlus","MaxApertureValue":1.53,"Model":"ONEPLUS A6003","Orientation|int":"1","PixelXDimension|int":"4608","PixelYDimension|int":"3456","SceneCaptureType|int":"0","SceneType|int":"1","ShutterSpeedValue":5.643,"SubSecTime":"591172","SubSecTimeDigitized":"591172","SubSecTimeOriginal":"591172","YCbCrPositioning|int":"1"}}}
